pyimps/__init__.py
pyimps/pyimps.py
pyimps-0.0.6.dist-info/METADATA
pyimps-0.0.6.dist-info/WHEEL
pyimps-0.0.6.dist-info/entry_points.txt
pyimps-0.0.6.dist-info/top_level.txt
pyimps-0.0.6.dist-info/RECORD
