Metadata-Version: 2.1
Name: pyimps
Version: 0.0.6
Summary: Unconfuse your Py imports
Home-page: https://github.com/bedbad/pyimps
Author: bedbad
Author-email: antonyuk@bu.edu
Classifier: Programming Language :: Python :: 3
Classifier: License :: OSI Approved :: GNU General Public License v3 (GPLv3)
Classifier: Operating System :: OS Independent
Requires-Dist: requests
